{"version":1,"resource":"file:///c%3A/Users/rafal/OneDrive/%C3%81rea%20de%20Trabalho/Rafa/Cubos/frontend/front-integral-mais-propriedades/classe-02/style.css","entries":[{"id":"VHQK.css","timestamp":1652382856274},{"id":"dZhK.css","timestamp":1652383138713},{"id":"iIlJ.css","timestamp":1652383174100},{"id":"QF9O.css","source":"undoRedo.source","timestamp":1652388470643},{"id":"W451.css","timestamp":1652396253311},{"id":"IgCF.css","timestamp":1652396497351},{"id":"vOuV.css","timestamp":1652396605676},{"id":"O6FS.css","source":"undoRedo.source","timestamp":1652396609601},{"id":"X3m6.css","timestamp":1652396618890},{"id":"mCvB.css","timestamp":1652396679707},{"id":"N6yL.css","timestamp":1652396700916},{"id":"0BzK.css","source":"undoRedo.source","timestamp":1652396709276},{"id":"tGZP.css","timestamp":1652396787966},{"id":"8BcE.css","timestamp":1652396813183},{"id":"oiuc.css","source":"undoRedo.source","timestamp":1652396901114},{"id":"E72k.css","timestamp":1652396910486},{"id":"wTKA.css","timestamp":1652396957071},{"id":"1cWW.css","source":"undoRedo.source","timestamp":1652396970171},{"id":"Qq0Q.css","timestamp":1652396996392},{"id":"yAfe.css","timestamp":1652397015694},{"id":"zk6D.css","timestamp":1652397052766},{"id":"7nL1.css","timestamp":1652397086496},{"id":"rLTZ.css","timestamp":1652397199932},{"id":"xu7F.css","timestamp":1652397217187},{"id":"C3vZ.css","timestamp":1652397276382},{"id":"F1jq.css","source":"undoRedo.source","timestamp":1652397279313},{"id":"QeHV.css","timestamp":1652397291581},{"id":"F4SZ.css","timestamp":1652397321735},{"id":"d774.css","source":"undoRedo.source","timestamp":1652397327446},{"id":"g9Gp.css","timestamp":1652397364213},{"id":"SdVg.css","timestamp":1652397427499},{"id":"VEE2.css","timestamp":1652397444537},{"id":"4U3g.css","timestamp":1652397574544},{"id":"Hjk8.css","timestamp":1652397586730},{"id":"ILvK.css","timestamp":1652397604324},{"id":"QqHW.css","timestamp":1652397621039},{"id":"qgsf.css","timestamp":1652397633468},{"id":"lCSa.css","timestamp":1652397776990},{"id":"1oC8.css","timestamp":1652397821194},{"id":"fsIs.css","timestamp":1652397848936},{"id":"hMYB.css","timestamp":1652397892146},{"id":"kU6x.css","timestamp":1652397934520},{"id":"GspF.css","timestamp":1652397966865},{"id":"36yN.css","timestamp":1652398041903},{"id":"e6sw.css","timestamp":1652398062458},{"id":"JpE8.css","timestamp":1652398118025},{"id":"yI4v.css","timestamp":1652398171253},{"id":"tfiG.css","timestamp":1652398187976},{"id":"rVFU.css","timestamp":1652398201915},{"id":"6t6d.css","timestamp":1652398315563}]}